[{"number": "168", "name": "Ariados", "species": "Long Leg", "types": ["Bug", "Poison"], "abilities": {"normal": ["Swarm", "Insomnia"], "hidden": ["Sniper"]}, "eggGroups": ["Bug"], "gender": [50, 50], "height": "3'07\"", "weight": "73.9 lbs.", "family": {"id": 85, "evolutionStage": 2, "evolutionLine": ["Spinarak", "Ariados"]}, "starter": false, "legendary": false, "mythical": false, "ultraBeast": false, "mega": false, "gen": 2, "sprite": "https://cdn.traction.one/pokedex/pokemon/168.png", "description": "Rather than making a nest in one specific spot, it wanders in search of food after darkness falls."}]