[{"number": "400", "name": "Bibarel", "species": "Beaver", "types": ["Normal", "Water"], "abilities": {"normal": ["Simple", "Unaware"], "hidden": ["Moody"]}, "eggGroups": ["Water 1", "Field"], "gender": [50, 50], "height": "3'03\"", "weight": "69.4 lbs.", "family": {"id": 207, "evolutionStage": 2, "evolutionLine": ["Bidoof", "Bibarel"]}, "starter": false, "legendary": false, "mythical": false, "ultraBeast": false, "mega": false, "gen": 4, "sprite": "https://cdn.traction.one/pokedex/pokemon/400.png", "description": "While its movements out of water are sluggish, it can swim as fast as any FEEBAS."}]