[{"number": "239", "name": "Elekid", "species": "Electric", "types": ["Electric"], "abilities": {"normal": ["Static"], "hidden": ["Vital Spirit"]}, "eggGroups": ["Undiscovered"], "gender": [75, 25], "height": "2'", "weight": "51.8 lbs.", "family": {"id": 60, "evolutionStage": 1, "evolutionLine": ["Elekid", "Electabuzz", "Electivire"]}, "starter": false, "legendary": false, "mythical": false, "ultraBeast": false, "mega": false, "gen": 2, "sprite": "https://cdn.traction.one/pokedex/pokemon/239.png", "description": "It loves violent thunder. The space between its horns flickers bluish-white when it is charging energy."}]