[{"number": "187", "name": "Hoppip", "species": "Cottonweed", "types": ["Grass", "Flying"], "abilities": {"normal": ["Chlorophyll", "Leaf Guard"], "hidden": ["Infiltrator"]}, "eggGroups": ["Fairy", "Grass"], "gender": [50, 50], "height": "1'04\"", "weight": "1.1 lbs.", "family": {"id": 92, "evolutionStage": 1, "evolutionLine": ["Hoppip", "Skiploom", "Jumpluff"]}, "starter": false, "legendary": false, "mythical": false, "ultraBeast": false, "mega": false, "gen": 2, "sprite": "https://cdn.traction.one/pokedex/pokemon/187.png", "description": "It can be carried away on even the gentlest breeze. It may even float all the way to the next town."}]