[{"number": "451", "name": "Skorupi", "species": "Scorpion", "types": ["Poison", "Bug"], "abilities": {"normal": ["Battle Armor", "Sniper"], "hidden": ["Keen Eye"]}, "eggGroups": ["Bug", "Water 3"], "gender": [50, 50], "height": "2'07\"", "weight": "26.5 lbs.", "family": {"id": 227, "evolutionStage": 1, "evolutionLine": ["Skorupi", "Drapion"]}, "starter": false, "legendary": false, "mythical": false, "ultraBeast": false, "mega": false, "gen": 4, "sprite": "https://cdn.traction.one/pokedex/pokemon/451.png", "description": "It grips prey with its tail claws and injects poison. It tenaciously hangs on until the poison takes."}]