[{"number": "289", "name": "Slaking", "species": "Lazy", "types": ["Normal"], "abilities": {"normal": ["Truant"], "hidden": []}, "eggGroups": ["Field"], "gender": [50, 50], "height": "6'07\"", "weight": "287.7 lbs.", "family": {"id": 143, "evolutionStage": 3, "evolutionLine": ["Slakoth", "Vigoroth", "Slaking"]}, "starter": false, "legendary": false, "mythical": false, "ultraBeast": false, "mega": false, "gen": 3, "sprite": "https://cdn.traction.one/pokedex/pokemon/289.png", "description": "SLAKING spends all day lying down and lolling about. It eats grass growing within its reach. If it eats all the grass it can reach, this POK\u00e9MON reluctantly moves to another spot."}]