[{"number": "191", "name": "Sunkern", "species": "Seed", "types": ["Grass"], "abilities": {"normal": ["Chlorophyll", "Solar Power"], "hidden": ["Early Bird"]}, "eggGroups": ["Grass"], "gender": [50, 50], "height": "1'", "weight": "4 lbs.", "family": {"id": 94, "evolutionStage": 1, "evolutionLine": ["Sunkern", "Sunflora"]}, "starter": false, "legendary": false, "mythical": false, "ultraBeast": false, "mega": false, "gen": 2, "sprite": "https://cdn.traction.one/pokedex/pokemon/191.png", "description": "It is very weak. Its only means of defense is to shake its leaves desperately at its attacker."}]